md2nb.py
md2nb/__init__.py
md2nb/md2nb.py
md2nb-0.2.0.dist-info/LICENSE
md2nb-0.2.0.dist-info/LICENSE.ipynb
md2nb-0.2.0.dist-info/METADATA
md2nb-0.2.0.dist-info/WHEEL
md2nb-0.2.0.dist-info/entry_points.txt
md2nb-0.2.0.dist-info/top_level.txt
md2nb-0.2.0.dist-info/RECORD
