Metadata-Version: 2.1
Name: md2nb
Version: 0.2.0
Summary: Convert Markdown files to Jupyter notebooks with a single Markdown block
Home-page: https://github.com/qin-yu/md2nb
Author: Qin Yu
Author-email: qin.yu@embl.de
License: bsd-3-clause
Keywords: markdown jupyter notebook md ipynb
Platform: UNKNOWN
Classifier: Programming Language :: Python :: 3
Classifier: License :: OSI Approved :: BSD License
Classifier: Operating System :: OS Independent
Classifier: Topic :: Text Processing :: Markup :: Markdown
Requires-Python: >=3.6
Requires-Dist: chardet
